sideways/__init__.py
sideways/aacparse.py
sideways/sideways.py
sideways/splitstream.py
sideways-0.0.23.data/scripts/sideways
sideways-0.0.23.dist-info/LICENSE
sideways-0.0.23.dist-info/METADATA
sideways-0.0.23.dist-info/WHEEL
sideways-0.0.23.dist-info/top_level.txt
sideways-0.0.23.dist-info/RECORD
