Metadata-Version: 2.1
Name: sideways
Version: 0.0.23
Summary: SCTE-35 Injection for Adaptive BitRate HLS 
Home-page: https://github.com/futzu/sideways
Author: Adrian of Doom
Author-email: spam@iodisco.com
Classifier: License :: OSI Approved :: MIT License
Classifier: Operating System :: OS Independent
Classifier: Programming Language :: Python :: 3.6
Classifier: Programming Language :: Python :: Implementation :: PyPy
Classifier: Programming Language :: Python :: Implementation :: CPython
Requires-Python: >=3.6
License-File: LICENSE
Requires-Dist: iframes (>=0.0.7)
Requires-Dist: m3ufu (>=0.0.87)
Requires-Dist: new-reader (>=0.1.7)
Requires-Dist: threefive (>=2.4.25)
Requires-Dist: umzz (>=0.0.31)
Requires-Dist: x9k3 (>=0.2.57)
